<annotation>
	<folder>family mart</folder>
	<filename>family mart_35.6525825_139.6361886_60.png</filename>
	<path>C:\family mart\family mart_35.6525825_139.6361886_60.png</path>
	<source>
		<database>Unknown</database>
	</source>
	<size>
		<width>0</width>
		<height>0</height>
		<depth>3</depth>
	</size>
	<segmented>0</segmented>
	<object>
		<name>family_mart</name>
		<pose>Unspecified</pose>
		<truncated>1</truncated>
		<difficult>0</difficult>
		<bndbox>
			<xmin>1</xmin>
			<ymin>208</ymin>
			<xmax>284</xmax>
			<ymax>298</ymax>
		</bndbox>
	</object>
	<object>
		<name>family_mart</name>
		<pose>Unspecified</pose>
		<truncated>0</truncated>
		<difficult>0</difficult>
		<bndbox>
			<xmin>30</xmin>
			<ymin>228</ymin>
			<xmax>185</xmax>
			<ymax>283</ymax>
		</bndbox>
	</object>
	<object>
		<name>family_mart</name>
		<pose>Unspecified</pose>
		<truncated>0</truncated>
		<difficult>0</difficult>
		<bndbox>
			<xmin>105</xmin>
			<ymin>322</ymin>
			<xmax>128</xmax>
			<ymax>422</ymax>
		</bndbox>
	</object>
	<object>
		<name>family_mart</name>
		<pose>Unspecified</pose>
		<truncated>0</truncated>
		<difficult>0</difficult>
		<bndbox>
			<xmin>299</xmin>
			<ymin>2</ymin>
			<xmax>340</xmax>
			<ymax>144</ymax>
		</bndbox>
	</object>
</annotation>
