<annotation>
	<folder>lawson</folder>
	<filename>lawson_35.77397310000001_139.5952813_300.png</filename>
	<path>C:\lawson\lawson_35.77397310000001_139.5952813_300.png</path>
	<source>
		<database>Unknown</database>
	</source>
	<size>
		<width>0</width>
		<height>0</height>
		<depth>3</depth>
	</size>
	<segmented>0</segmented>
	<object>
		<name>lawson</name>
		<pose>Unspecified</pose>
		<truncated>0</truncated>
		<difficult>0</difficult>
		<bndbox>
			<xmin>163</xmin>
			<ymin>257</ymin>
			<xmax>195</xmax>
			<ymax>290</ymax>
		</bndbox>
	</object>
</annotation>
